LICENSE.txt
MANIFEST.in
pyproject.toml
requirements.txt
setup.py
src/extension/call.pxi
src/extension/callback.pxi
src/extension/cmp.pxi
src/extension/csleqp.pxd
src/extension/dyn.pxi
src/extension/func.pxi
src/extension/gil.pxi
src/extension/hess_struct.pxi
src/extension/iterate.pxi
src/extension/log.pxi
src/extension/lsq.pxi
src/extension/problem.pxi
src/extension/scale.pxi
src/extension/settings.pxi
src/extension/sleqp.pyx
src/extension/solver.pxi
src/extension/sparse.pxi
src/extension/sparse_matrix.pxi
src/extension/types.pxi
src/extension/version.pxi
src/extension/working_set.pxi
src/sleqp/__init__.py
src/sleqp/_bounds.py
src/sleqp/_cons.py
src/sleqp/_cons_func.py
src/sleqp/_derivative.py
src/sleqp/_func.py
src/sleqp/_hessian.py
src/sleqp/_linear.py
src/sleqp/minimize.py
src/sleqp.egg-info/PKG-INFO
src/sleqp.egg-info/SOURCES.txt
src/sleqp.egg-info/dependency_links.txt
src/sleqp.egg-info/requires.txt
src/sleqp.egg-info/top_level.txt