Metadata-Version: 2.1
Name: sleqp
Version: 1.0.0
Summary: Active set-based NLP solver
Author: Christoph Hansknecht
Author-email: c.hansknecht@tu-braunschweig.de
Classifier: Programming Language :: Cython
Classifier: Intended Audience :: Science/Research
Classifier: Topic :: Scientific/Engineering :: Mathematics
License-File: LICENSE.txt
